HyTechMaster_STT/__init__.py
hytechmaster-0.1.1.dist-info/METADATA
hytechmaster-0.1.1.dist-info/WHEEL
hytechmaster-0.1.1.dist-info/top_level.txt
hytechmaster-0.1.1.dist-info/RECORD
