Metadata-Version: 2.4
Name: HyTechMaster
Version: 0.1.1
Summary: This is speech to text package created by arman rathore
Author-email: armanrathore236@gmail.com
Dynamic: author-email
Dynamic: summary
